hausmon_client/__init__.py
hausmon_client/client.py
tests/__init__.py
tests/client_tests.py
hausmon_client-0.0.6.dist-info/LICENSE
hausmon_client-0.0.6.dist-info/METADATA
hausmon_client-0.0.6.dist-info/WHEEL
hausmon_client-0.0.6.dist-info/top_level.txt
hausmon_client-0.0.6.dist-info/RECORD
