Metadata-Version: 2.1
Name: hausmon-client
Version: 0.0.6
Summary: A client for the HausMon monitoring service
Home-page: https://github.com/HausNet/hausmon-client
Author: Louis Calitz
Author-email: louis@hausnet.io
License: UNKNOWN
Platform: UNKNOWN
Classifier: Programming Language :: Python :: 3
Classifier: License :: OSI Approved :: MIT License
Classifier: Operating System :: OS Independent
Requires-Python: >=3.8
Requires-Dist: bravado
